iga/__init__.py
iga/__main__.py
iga/cli.py
iga/data_utils.py
iga/doi.py
iga/exceptions.py
iga/exit_codes.py
iga/github.py
iga/id_utils.py
iga/invenio.py
iga/json_utils.py
iga/licenses.py
iga/metadata.py
iga/name_utils.py
iga/orcid.py
iga/reference.py
iga/ror.py
iga/text_utils.py
iga-1.3.5.dist-info/LICENSE
iga-1.3.5.dist-info/METADATA
iga-1.3.5.dist-info/WHEEL
iga-1.3.5.dist-info/entry_points.txt
iga-1.3.5.dist-info/top_level.txt
iga-1.3.5.dist-info/RECORD
