Metadata-Version: 2.1
Name: iga
Version: 1.3.5
Summary: The InvenioRDM GitHub Archiver (IGA) automatically archives GitHub releases in an InvenioRDM repository.
Home-page: https://github.com/caltechlibrary/iga
Author: Tom Morrell
Author-email: tmorrell@caltech.edu
License: https://github.com/caltechlibrary/iga/blob/main/LICENSE
Project-URL: Source Code, https://github.com/caltechlibrary/iga
Project-URL: Bug Tracker, https://github.com/caltechlibrary/iga/issues
Keywords: Python,applications
Platform: UNKNOWN
Classifier: Development Status :: 5 - Production/Stable
Classifier: Environment :: Console
Classifier: Environment :: No Input/Output (Daemon)
Classifier: Intended Audience :: Science/Research
Classifier: Operating System :: MacOS :: MacOS X
Classifier: Operating System :: POSIX
Classifier: Operating System :: POSIX :: Linux
Classifier: Operating System :: Unix
Classifier: Programming Language :: Python
Classifier: Programming Language :: Python :: 3.9
Requires-Python: >=3.9
License-File: LICENSE
Requires-Dist: aenum>=3.1.15
Requires-Dist: arrow>=1.3.0
Requires-Dist: boltons>=21.0.0
Requires-Dist: caltechdata-api>=1.8.1
Requires-Dist: commonpy>=1.13.0
Requires-Dist: dirtyjson>=1.0.8
Requires-Dist: ginza>=5.2.0
Requires-Dist: ja-ginza-electra>=5.2.0
Requires-Dist: httpx>=0.23.1
Requires-Dist: humanize>=4.9.0
Requires-Dist: idutils>=1.2.1
Requires-Dist: iptools>=0.7.0
Requires-Dist: isbnlib>=3.10.14
Requires-Dist: jamo>=0.4.1
Requires-Dist: json5>=0.9.25
Requires-Dist: latexcodec>=3.0.0
Requires-Dist: lingua-language-detector>=2.0.2
Requires-Dist: lxml>=5.2.2
Requires-Dist: Markdown>=3.6
Requires-Dist: markdown-checklist>=0.4.4
Requires-Dist: mdx-breakless-lists>=1.0.1
Requires-Dist: mdx-linkify>=2.1
Requires-Dist: nameparser>=1.1.3
Requires-Dist: probablepeople>=0.5.5
Requires-Dist: pybtex>=0.24.0
Requires-Dist: pybtex-apa7-style>=0.1.3
Requires-Dist: pymdown-extensions>=10.8.1
Requires-Dist: PyYAML>=6.0.1
Requires-Dist: regex>=2022.3.2
Requires-Dist: rich-click==1.7.4
Requires-Dist: sidetrack>=2.0.1
Requires-Dist: spacy>=3.7.4
Requires-Dist: spacy-alignments>=0.9.1
Requires-Dist: spacy-curated-transformers>=0.2.2
Requires-Dist: spacy-legacy>=3.0.12
Requires-Dist: spacy-loggers>=1.0.5
Requires-Dist: spacy-pkuseg>=0.0.33
Requires-Dist: spacy-transformers>=1.1.9
Requires-Dist: StringDist>=1.0.9
Requires-Dist: url-normalize>=1.4.3
Requires-Dist: validators>=0.28.1
